functorch
torch
torchaudio
torchgen
torchvision
torio
