Metadata-Version: 2.4
Name: torch-aipy
Version: 2.5.0.6
Summary: Tensors and Dynamic neural networks in Python with strong GPU acceleration
Home-page: https://qpypi.qpython.org/project/torch-aipy/
Author: The QPYPI Team
Author-email: qpypi@qpython.org
License: OSI Approved :: BSD License
Classifier: Intended Audience :: Developers
Classifier: Intended Audience :: Education
Classifier: Intended Audience :: Information Technology
Classifier: Intended Audience :: End Users/Desktop
Classifier: License :: OSI Approved :: Apache Software License
Classifier: Operating System :: Android
Classifier: Programming Language :: Python
Classifier: Programming Language :: Python :: 3.12
Classifier: Topic :: Software Development
Requires-Python: ==3.12.*
Requires-Dist: pillow-qpython
Requires-Dist: numpy-aipy
Requires-Dist: typing-extensions-qpython
Requires-Dist: sympy
Requires-Dist: networkx
Requires-Dist: mpmath
Requires-Dist: fsspec
Requires-Dist: filelock
Dynamic: author
Dynamic: author-email
Dynamic: classifier
Dynamic: description
Dynamic: description-content-type
Dynamic: home-page
Dynamic: license
Dynamic: requires-dist
Dynamic: requires-python
Dynamic: summary
